{"indexes":[],"parameters":{"allowUserKeys":true,"cacheEnabled":false,"cid":"161","deleted":false,"globallyUniqueId":"h630CDA0CE3C/161","id":"161","isDisjoint":false,"isSmart":false,"isSmartChild":false,"isSystem":false,"keyOptions":{"allowUserKeys":true,"type":"traditional","lastValue":25524},"minReplicationFactor":1,"minRevision":"_cmVtEu6---","name":"restaurants","numberOfShards":1,"planId":"161","replicationFactor":1,"schema":null,"shardKeys":["_key"],"shards":{},"status":3,"syncByRevision":true,"type":2,"usesRevisionsAsDocumentIds":true,"version":9,"waitForSync":false,"writeConcern":1}}